[
  {
    "batch_size": 256,
    "type": "vdd_gpu_avg",
    "value": 1612.3833333333337
  },
  {
    "batch_size": 256,
    "type": "vdd_cpu_avg",
    "value": 0.0
  },
  {
    "batch_size": 256,
    "type": "vin_sys_avg",
    "value": 1115.6333333333337
  },
  {
    "batch_size": 512,
    "type": "vdd_gpu_avg",
    "value": 1746.0500000000002
  },
  {
    "batch_size": 512,
    "type": "vdd_cpu_avg",
    "value": 0.11666666666667425
  },
  {
    "batch_size": 512,
    "type": "vin_sys_avg",
    "value": 1148.6166666666663
  }
]