[
  {
    "timestamp": "2025-11-05T10:03:26",
    "ram_used": 15124,
    "ram_total": 62841,
    "batch_size": 4,
    "bar_start_end": false
  },
  {
    "timestamp": "2025-11-05T10:03:27",
    "ram_used": 15123,
    "ram_total": 62841,
    "batch_size": 4,
    "bar_start_end": false
  },
  {
    "timestamp": "2025-11-05T10:03:28",
    "ram_used": 15124,
    "ram_total": 62841,
    "batch_size": 4,
    "bar_start_end": false
  },
  {
    "timestamp": "2025-11-05T10:03:29",
    "ram_used": 15123,
    "ram_total": 62841,
    "batch_size": 4,
    "bar_start_end": false
  },
  {
    "timestamp": "2025-11-05T10:03:30",
    "ram_used": 15123,
    "ram_total": 62841,
    "batch_size": 4,
    "bar_start_end": true
  },
  {
    "timestamp": "2025-11-05T10:03:31",
    "ram_used": 15125,
    "ram_total": 62841,
    "batch_size": 4,
    "bar_start_end": false
  },
  {
    "timestamp": "2025-11-05T10:03:32",
    "ram_used": 15125,
    "ram_total": 62841,
    "batch_size": 4,
    "bar_start_end": false
  },
  {
    "timestamp": "2025-11-05T10:03:33",
    "ram_used": 15126,
    "ram_total": 62841,
    "batch_size": 4,
    "bar_start_end": false
  },
  {
    "timestamp": "2025-11-05T10:03:34",
    "ram_used": 15126,
    "ram_total": 62841,
    "batch_size": 4,
    "bar_start_end": false
  },
  {
    "timestamp": "2025-11-05T10:03:35",
    "ram_used": 15126,
    "ram_total": 62841,
    "batch_size": 4,
    "bar_start_end": false
  },
  {
    "timestamp": "2025-11-05T10:03:36",
    "ram_used": 15114,
    "ram_total": 62841,
    "batch_size": 4,
    "bar_start_end": false
  },
  {
    "timestamp": "2025-11-05T10:03:37",
    "ram_used": 15114,
    "ram_total": 62841,
    "batch_size": 4,
    "bar_start_end": false
  },
  {
    "timestamp": "2025-11-05T10:03:38",
    "ram_used": 15114,
    "ram_total": 62841,
    "batch_size": 4,
    "bar_start_end": false
  },
  {
    "timestamp": "2025-11-05T10:03:39",
    "ram_used": 15114,
    "ram_total": 62841,
    "batch_size": 4,
    "bar_start_end": false
  },
  {
    "timestamp": "2025-11-05T10:03:40",
    "ram_used": 15114,
    "ram_total": 62841,
    "batch_size": 4,
    "bar_start_end": false
  },
  {
    "timestamp": "2025-11-05T10:03:41",
    "ram_used": 15114,
    "ram_total": 62841,
    "batch_size": 4,
    "bar_start_end": false
  },
  {
    "timestamp": "2025-11-05T10:03:42",
    "ram_used": 15114,
    "ram_total": 62841,
    "batch_size": 4,
    "bar_start_end": false
  },
  {
    "timestamp": "2025-11-05T10:03:43",
    "ram_used": 15114,
    "ram_total": 62841,
    "batch_size": 4,
    "bar_start_end": false
  },
  {
    "timestamp": "2025-11-05T10:03:44",
    "ram_used": 15114,
    "ram_total": 62841,
    "batch_size": 4,
    "bar_start_end": false
  },
  {
    "timestamp": "2025-11-05T10:03:45",
    "ram_used": 15114,
    "ram_total": 62841,
    "batch_size": 4,
    "bar_start_end": false
  },
  {
    "timestamp": "2025-11-05T10:03:46",
    "ram_used": 15114,
    "ram_total": 62841,
    "batch_size": 4,
    "bar_start_end": false
  },
  {
    "timestamp": "2025-11-05T10:03:47",
    "ram_used": 15114,
    "ram_total": 62841,
    "batch_size": 4,
    "bar_start_end": false
  },
  {
    "timestamp": "2025-11-05T10:03:48",
    "ram_used": 15114,
    "ram_total": 62841,
    "batch_size": 4,
    "bar_start_end": false
  },
  {
    "timestamp": "2025-11-05T10:03:49",
    "ram_used": 15114,
    "ram_total": 62841,
    "batch_size": 4,
    "bar_start_end": false
  },
  {
    "timestamp": "2025-11-05T10:03:50",
    "ram_used": 15114,
    "ram_total": 62841,
    "batch_size": 4,
    "bar_start_end": false
  },
  {
    "timestamp": "2025-11-05T10:03:51",
    "ram_used": 15114,
    "ram_total": 62841,
    "batch_size": 4,
    "bar_start_end": false
  },
  {
    "timestamp": "2025-11-05T10:03:52",
    "ram_used": 15114,
    "ram_total": 62841,
    "batch_size": 4,
    "bar_start_end": false
  },
  {
    "timestamp": "2025-11-05T10:03:53",
    "ram_used": 15114,
    "ram_total": 62841,
    "batch_size": 4,
    "bar_start_end": false
  },
  {
    "timestamp": "2025-11-05T10:03:54",
    "ram_used": 15114,
    "ram_total": 62841,
    "batch_size": 4,
    "bar_start_end": false
  },
  {
    "timestamp": "2025-11-05T10:03:55",
    "ram_used": 15114,
    "ram_total": 62841,
    "batch_size": 4,
    "bar_start_end": false
  },
  {
    "timestamp": "2025-11-05T10:03:56",
    "ram_used": 15113,
    "ram_total": 62841,
    "batch_size": 4,
    "bar_start_end": false
  },
  {
    "timestamp": "2025-11-05T10:03:57",
    "ram_used": 15113,
    "ram_total": 62841,
    "batch_size": 4,
    "bar_start_end": false
  },
  {
    "timestamp": "2025-11-05T10:03:58",
    "ram_used": 15113,
    "ram_total": 62841,
    "batch_size": 4,
    "bar_start_end": true
  },
  {
    "timestamp": "2025-11-05T10:03:59",
    "ram_used": 15113,
    "ram_total": 62841,
    "batch_size": 4,
    "bar_start_end": false
  },
  {
    "timestamp": "2025-11-05T10:04:00",
    "ram_used": 15113,
    "ram_total": 62841,
    "batch_size": 4,
    "bar_start_end": false
  },
  {
    "timestamp": "2025-11-05T10:04:01",
    "ram_used": 15113,
    "ram_total": 62841,
    "batch_size": 4,
    "bar_start_end": false
  },
  {
    "timestamp": "2025-11-05T10:04:02",
    "ram_used": 15113,
    "ram_total": 62841,
    "batch_size": 4,
    "bar_start_end": false
  },
  {
    "timestamp": "2025-11-05T10:04:03",
    "ram_used": 15114,
    "ram_total": 62841,
    "batch_size": 4,
    "bar_start_end": false
  },
  {
    "timestamp": "2025-11-05T10:04:04",
    "ram_used": 15115,
    "ram_total": 62841,
    "batch_size": 4,
    "bar_start_end": false
  },
  {
    "timestamp": "2025-11-05T10:04:06",
    "ram_used": 15115,
    "ram_total": 62841,
    "batch_size": 4,
    "bar_start_end": false
  },
  {
    "timestamp": "2025-11-05T10:04:07",
    "ram_used": 15115,
    "ram_total": 62841,
    "batch_size": 4,
    "bar_start_end": false
  },
  {
    "timestamp": "2025-11-05T10:04:08",
    "ram_used": 15115,
    "ram_total": 62841,
    "batch_size": 4,
    "bar_start_end": false
  },
  {
    "timestamp": "2025-11-05T10:04:18",
    "ram_used": 15122,
    "ram_total": 62841,
    "batch_size": 8,
    "bar_start_end": false
  },
  {
    "timestamp": "2025-11-05T10:04:19",
    "ram_used": 15122,
    "ram_total": 62841,
    "batch_size": 8,
    "bar_start_end": false
  },
  {
    "timestamp": "2025-11-05T10:04:20",
    "ram_used": 15122,
    "ram_total": 62841,
    "batch_size": 8,
    "bar_start_end": false
  },
  {
    "timestamp": "2025-11-05T10:04:21",
    "ram_used": 15122,
    "ram_total": 62841,
    "batch_size": 8,
    "bar_start_end": false
  },
  {
    "timestamp": "2025-11-05T10:04:22",
    "ram_used": 15123,
    "ram_total": 62841,
    "batch_size": 8,
    "bar_start_end": false
  },
  {
    "timestamp": "2025-11-05T10:04:23",
    "ram_used": 15123,
    "ram_total": 62841,
    "batch_size": 8,
    "bar_start_end": false
  },
  {
    "timestamp": "2025-11-05T10:04:24",
    "ram_used": 15122,
    "ram_total": 62841,
    "batch_size": 8,
    "bar_start_end": false
  },
  {
    "timestamp": "2025-11-05T10:04:25",
    "ram_used": 15122,
    "ram_total": 62841,
    "batch_size": 8,
    "bar_start_end": false
  },
  {
    "timestamp": "2025-11-05T10:04:26",
    "ram_used": 15122,
    "ram_total": 62841,
    "batch_size": 8,
    "bar_start_end": false
  },
  {
    "timestamp": "2025-11-05T10:04:27",
    "ram_used": 15122,
    "ram_total": 62841,
    "batch_size": 8,
    "bar_start_end": false
  },
  {
    "timestamp": "2025-11-05T10:04:28",
    "ram_used": 15124,
    "ram_total": 62841,
    "batch_size": 8,
    "bar_start_end": true
  },
  {
    "timestamp": "2025-11-05T10:04:29",
    "ram_used": 15124,
    "ram_total": 62841,
    "batch_size": 8,
    "bar_start_end": false
  },
  {
    "timestamp": "2025-11-05T10:04:30",
    "ram_used": 15124,
    "ram_total": 62841,
    "batch_size": 8,
    "bar_start_end": false
  },
  {
    "timestamp": "2025-11-05T10:04:31",
    "ram_used": 15124,
    "ram_total": 62841,
    "batch_size": 8,
    "bar_start_end": false
  },
  {
    "timestamp": "2025-11-05T10:04:32",
    "ram_used": 15124,
    "ram_total": 62841,
    "batch_size": 8,
    "bar_start_end": false
  },
  {
    "timestamp": "2025-11-05T10:04:34",
    "ram_used": 15124,
    "ram_total": 62841,
    "batch_size": 8,
    "bar_start_end": false
  },
  {
    "timestamp": "2025-11-05T10:04:35",
    "ram_used": 15124,
    "ram_total": 62841,
    "batch_size": 8,
    "bar_start_end": false
  },
  {
    "timestamp": "2025-11-05T10:04:36",
    "ram_used": 15151,
    "ram_total": 62841,
    "batch_size": 8,
    "bar_start_end": false
  },
  {
    "timestamp": "2025-11-05T10:04:37",
    "ram_used": 15151,
    "ram_total": 62841,
    "batch_size": 8,
    "bar_start_end": false
  },
  {
    "timestamp": "2025-11-05T10:04:38",
    "ram_used": 15152,
    "ram_total": 62841,
    "batch_size": 8,
    "bar_start_end": false
  },
  {
    "timestamp": "2025-11-05T10:04:39",
    "ram_used": 15152,
    "ram_total": 62841,
    "batch_size": 8,
    "bar_start_end": false
  },
  {
    "timestamp": "2025-11-05T10:04:40",
    "ram_used": 15152,
    "ram_total": 62841,
    "batch_size": 8,
    "bar_start_end": false
  },
  {
    "timestamp": "2025-11-05T10:04:41",
    "ram_used": 15152,
    "ram_total": 62841,
    "batch_size": 8,
    "bar_start_end": false
  },
  {
    "timestamp": "2025-11-05T10:04:42",
    "ram_used": 15153,
    "ram_total": 62841,
    "batch_size": 8,
    "bar_start_end": false
  },
  {
    "timestamp": "2025-11-05T10:04:43",
    "ram_used": 15153,
    "ram_total": 62841,
    "batch_size": 8,
    "bar_start_end": true
  },
  {
    "timestamp": "2025-11-05T10:04:44",
    "ram_used": 15153,
    "ram_total": 62841,
    "batch_size": 8,
    "bar_start_end": false
  },
  {
    "timestamp": "2025-11-05T10:04:45",
    "ram_used": 15153,
    "ram_total": 62841,
    "batch_size": 8,
    "bar_start_end": false
  },
  {
    "timestamp": "2025-11-05T10:04:46",
    "ram_used": 15153,
    "ram_total": 62841,
    "batch_size": 8,
    "bar_start_end": false
  },
  {
    "timestamp": "2025-11-05T10:04:47",
    "ram_used": 15153,
    "ram_total": 62841,
    "batch_size": 8,
    "bar_start_end": false
  },
  {
    "timestamp": "2025-11-05T10:04:48",
    "ram_used": 15153,
    "ram_total": 62841,
    "batch_size": 8,
    "bar_start_end": false
  },
  {
    "timestamp": "2025-11-05T10:04:49",
    "ram_used": 15153,
    "ram_total": 62841,
    "batch_size": 8,
    "bar_start_end": false
  },
  {
    "timestamp": "2025-11-05T10:04:50",
    "ram_used": 15153,
    "ram_total": 62841,
    "batch_size": 8,
    "bar_start_end": false
  },
  {
    "timestamp": "2025-11-05T10:04:51",
    "ram_used": 15153,
    "ram_total": 62841,
    "batch_size": 8,
    "bar_start_end": false
  },
  {
    "timestamp": "2025-11-05T10:04:52",
    "ram_used": 15153,
    "ram_total": 62841,
    "batch_size": 8,
    "bar_start_end": false
  },
  {
    "timestamp": "2025-11-05T10:04:53",
    "ram_used": 15153,
    "ram_total": 62841,
    "batch_size": 8,
    "bar_start_end": false
  },
  {
    "timestamp": "2025-11-05T10:05:03",
    "ram_used": 15177,
    "ram_total": 62841,
    "batch_size": 16,
    "bar_start_end": false
  },
  {
    "timestamp": "2025-11-05T10:05:04",
    "ram_used": 15176,
    "ram_total": 62841,
    "batch_size": 16,
    "bar_start_end": false
  },
  {
    "timestamp": "2025-11-05T10:05:05",
    "ram_used": 15176,
    "ram_total": 62841,
    "batch_size": 16,
    "bar_start_end": false
  },
  {
    "timestamp": "2025-11-05T10:05:06",
    "ram_used": 15177,
    "ram_total": 62841,
    "batch_size": 16,
    "bar_start_end": false
  },
  {
    "timestamp": "2025-11-05T10:05:07",
    "ram_used": 15177,
    "ram_total": 62841,
    "batch_size": 16,
    "bar_start_end": false
  },
  {
    "timestamp": "2025-11-05T10:05:08",
    "ram_used": 15176,
    "ram_total": 62841,
    "batch_size": 16,
    "bar_start_end": false
  },
  {
    "timestamp": "2025-11-05T10:05:09",
    "ram_used": 15176,
    "ram_total": 62841,
    "batch_size": 16,
    "bar_start_end": false
  },
  {
    "timestamp": "2025-11-05T10:05:10",
    "ram_used": 15176,
    "ram_total": 62841,
    "batch_size": 16,
    "bar_start_end": false
  },
  {
    "timestamp": "2025-11-05T10:05:11",
    "ram_used": 15176,
    "ram_total": 62841,
    "batch_size": 16,
    "bar_start_end": false
  },
  {
    "timestamp": "2025-11-05T10:05:12",
    "ram_used": 15177,
    "ram_total": 62841,
    "batch_size": 16,
    "bar_start_end": false
  },
  {
    "timestamp": "2025-11-05T10:05:13",
    "ram_used": 15177,
    "ram_total": 62841,
    "batch_size": 16,
    "bar_start_end": true
  },
  {
    "timestamp": "2025-11-05T10:05:14",
    "ram_used": 15178,
    "ram_total": 62841,
    "batch_size": 16,
    "bar_start_end": false
  },
  {
    "timestamp": "2025-11-05T10:05:15",
    "ram_used": 15177,
    "ram_total": 62841,
    "batch_size": 16,
    "bar_start_end": false
  },
  {
    "timestamp": "2025-11-05T10:05:16",
    "ram_used": 15177,
    "ram_total": 62841,
    "batch_size": 16,
    "bar_start_end": false
  },
  {
    "timestamp": "2025-11-05T10:05:17",
    "ram_used": 15177,
    "ram_total": 62841,
    "batch_size": 16,
    "bar_start_end": false
  },
  {
    "timestamp": "2025-11-05T10:05:18",
    "ram_used": 15178,
    "ram_total": 62841,
    "batch_size": 16,
    "bar_start_end": false
  },
  {
    "timestamp": "2025-11-05T10:05:19",
    "ram_used": 15177,
    "ram_total": 62841,
    "batch_size": 16,
    "bar_start_end": false
  },
  {
    "timestamp": "2025-11-05T10:05:20",
    "ram_used": 15178,
    "ram_total": 62841,
    "batch_size": 16,
    "bar_start_end": false
  },
  {
    "timestamp": "2025-11-05T10:05:21",
    "ram_used": 15177,
    "ram_total": 62841,
    "batch_size": 16,
    "bar_start_end": false
  },
  {
    "timestamp": "2025-11-05T10:05:23",
    "ram_used": 15178,
    "ram_total": 62841,
    "batch_size": 16,
    "bar_start_end": true
  },
  {
    "timestamp": "2025-11-05T10:05:24",
    "ram_used": 15177,
    "ram_total": 62841,
    "batch_size": 16,
    "bar_start_end": false
  },
  {
    "timestamp": "2025-11-05T10:05:25",
    "ram_used": 15178,
    "ram_total": 62841,
    "batch_size": 16,
    "bar_start_end": false
  },
  {
    "timestamp": "2025-11-05T10:05:26",
    "ram_used": 15177,
    "ram_total": 62841,
    "batch_size": 16,
    "bar_start_end": false
  },
  {
    "timestamp": "2025-11-05T10:05:27",
    "ram_used": 15177,
    "ram_total": 62841,
    "batch_size": 16,
    "bar_start_end": false
  },
  {
    "timestamp": "2025-11-05T10:05:28",
    "ram_used": 15174,
    "ram_total": 62841,
    "batch_size": 16,
    "bar_start_end": false
  },
  {
    "timestamp": "2025-11-05T10:05:29",
    "ram_used": 15174,
    "ram_total": 62841,
    "batch_size": 16,
    "bar_start_end": false
  },
  {
    "timestamp": "2025-11-05T10:05:30",
    "ram_used": 15174,
    "ram_total": 62841,
    "batch_size": 16,
    "bar_start_end": false
  },
  {
    "timestamp": "2025-11-05T10:05:31",
    "ram_used": 15174,
    "ram_total": 62841,
    "batch_size": 16,
    "bar_start_end": false
  },
  {
    "timestamp": "2025-11-05T10:05:32",
    "ram_used": 15174,
    "ram_total": 62841,
    "batch_size": 16,
    "bar_start_end": false
  },
  {
    "timestamp": "2025-11-05T10:05:33",
    "ram_used": 15174,
    "ram_total": 62841,
    "batch_size": 16,
    "bar_start_end": false
  },
  {
    "timestamp": "2025-11-05T10:05:34",
    "ram_used": 15174,
    "ram_total": 62841,
    "batch_size": 16,
    "bar_start_end": false
  },
  {
    "timestamp": "2025-11-05T10:05:43",
    "ram_used": 15196,
    "ram_total": 62841,
    "batch_size": 32,
    "bar_start_end": false
  },
  {
    "timestamp": "2025-11-05T10:05:44",
    "ram_used": 15195,
    "ram_total": 62841,
    "batch_size": 32,
    "bar_start_end": false
  },
  {
    "timestamp": "2025-11-05T10:05:45",
    "ram_used": 15195,
    "ram_total": 62841,
    "batch_size": 32,
    "bar_start_end": false
  },
  {
    "timestamp": "2025-11-05T10:05:47",
    "ram_used": 15195,
    "ram_total": 62841,
    "batch_size": 32,
    "bar_start_end": false
  },
  {
    "timestamp": "2025-11-05T10:05:48",
    "ram_used": 15195,
    "ram_total": 62841,
    "batch_size": 32,
    "bar_start_end": false
  },
  {
    "timestamp": "2025-11-05T10:05:49",
    "ram_used": 15194,
    "ram_total": 62841,
    "batch_size": 32,
    "bar_start_end": false
  },
  {
    "timestamp": "2025-11-05T10:05:50",
    "ram_used": 15194,
    "ram_total": 62841,
    "batch_size": 32,
    "bar_start_end": false
  },
  {
    "timestamp": "2025-11-05T10:05:51",
    "ram_used": 15194,
    "ram_total": 62841,
    "batch_size": 32,
    "bar_start_end": false
  },
  {
    "timestamp": "2025-11-05T10:05:52",
    "ram_used": 15194,
    "ram_total": 62841,
    "batch_size": 32,
    "bar_start_end": false
  },
  {
    "timestamp": "2025-11-05T10:05:53",
    "ram_used": 15196,
    "ram_total": 62841,
    "batch_size": 32,
    "bar_start_end": true
  },
  {
    "timestamp": "2025-11-05T10:05:54",
    "ram_used": 15195,
    "ram_total": 62841,
    "batch_size": 32,
    "bar_start_end": false
  },
  {
    "timestamp": "2025-11-05T10:05:55",
    "ram_used": 15195,
    "ram_total": 62841,
    "batch_size": 32,
    "bar_start_end": false
  },
  {
    "timestamp": "2025-11-05T10:05:56",
    "ram_used": 15195,
    "ram_total": 62841,
    "batch_size": 32,
    "bar_start_end": false
  },
  {
    "timestamp": "2025-11-05T10:05:57",
    "ram_used": 15195,
    "ram_total": 62841,
    "batch_size": 32,
    "bar_start_end": false
  },
  {
    "timestamp": "2025-11-05T10:05:58",
    "ram_used": 15195,
    "ram_total": 62841,
    "batch_size": 32,
    "bar_start_end": false
  },
  {
    "timestamp": "2025-11-05T10:05:59",
    "ram_used": 15188,
    "ram_total": 62841,
    "batch_size": 32,
    "bar_start_end": false
  },
  {
    "timestamp": "2025-11-05T10:06:00",
    "ram_used": 15188,
    "ram_total": 62841,
    "batch_size": 32,
    "bar_start_end": false
  },
  {
    "timestamp": "2025-11-05T10:06:01",
    "ram_used": 15188,
    "ram_total": 62841,
    "batch_size": 32,
    "bar_start_end": false
  },
  {
    "timestamp": "2025-11-05T10:06:02",
    "ram_used": 15188,
    "ram_total": 62841,
    "batch_size": 32,
    "bar_start_end": true
  },
  {
    "timestamp": "2025-11-05T10:06:03",
    "ram_used": 15189,
    "ram_total": 62841,
    "batch_size": 32,
    "bar_start_end": false
  },
  {
    "timestamp": "2025-11-05T10:06:04",
    "ram_used": 15189,
    "ram_total": 62841,
    "batch_size": 32,
    "bar_start_end": false
  },
  {
    "timestamp": "2025-11-05T10:06:05",
    "ram_used": 15189,
    "ram_total": 62841,
    "batch_size": 32,
    "bar_start_end": false
  },
  {
    "timestamp": "2025-11-05T10:06:06",
    "ram_used": 15188,
    "ram_total": 62841,
    "batch_size": 32,
    "bar_start_end": false
  },
  {
    "timestamp": "2025-11-05T10:06:07",
    "ram_used": 15189,
    "ram_total": 62841,
    "batch_size": 32,
    "bar_start_end": false
  },
  {
    "timestamp": "2025-11-05T10:06:08",
    "ram_used": 15189,
    "ram_total": 62841,
    "batch_size": 32,
    "bar_start_end": false
  },
  {
    "timestamp": "2025-11-05T10:06:09",
    "ram_used": 15189,
    "ram_total": 62841,
    "batch_size": 32,
    "bar_start_end": false
  },
  {
    "timestamp": "2025-11-05T10:06:10",
    "ram_used": 15189,
    "ram_total": 62841,
    "batch_size": 32,
    "bar_start_end": false
  },
  {
    "timestamp": "2025-11-05T10:06:11",
    "ram_used": 15189,
    "ram_total": 62841,
    "batch_size": 32,
    "bar_start_end": false
  },
  {
    "timestamp": "2025-11-05T10:06:12",
    "ram_used": 15189,
    "ram_total": 62841,
    "batch_size": 32,
    "bar_start_end": false
  },
  {
    "timestamp": "2025-11-05T10:06:23",
    "ram_used": 15209,
    "ram_total": 62841,
    "batch_size": 64,
    "bar_start_end": false
  },
  {
    "timestamp": "2025-11-05T10:06:24",
    "ram_used": 15209,
    "ram_total": 62841,
    "batch_size": 64,
    "bar_start_end": false
  },
  {
    "timestamp": "2025-11-05T10:06:25",
    "ram_used": 15210,
    "ram_total": 62841,
    "batch_size": 64,
    "bar_start_end": false
  },
  {
    "timestamp": "2025-11-05T10:06:26",
    "ram_used": 15209,
    "ram_total": 62841,
    "batch_size": 64,
    "bar_start_end": false
  },
  {
    "timestamp": "2025-11-05T10:06:27",
    "ram_used": 15209,
    "ram_total": 62841,
    "batch_size": 64,
    "bar_start_end": false
  },
  {
    "timestamp": "2025-11-05T10:06:28",
    "ram_used": 15209,
    "ram_total": 62841,
    "batch_size": 64,
    "bar_start_end": false
  },
  {
    "timestamp": "2025-11-05T10:06:29",
    "ram_used": 15209,
    "ram_total": 62841,
    "batch_size": 64,
    "bar_start_end": false
  },
  {
    "timestamp": "2025-11-05T10:06:30",
    "ram_used": 15209,
    "ram_total": 62841,
    "batch_size": 64,
    "bar_start_end": false
  },
  {
    "timestamp": "2025-11-05T10:06:31",
    "ram_used": 15209,
    "ram_total": 62841,
    "batch_size": 64,
    "bar_start_end": false
  },
  {
    "timestamp": "2025-11-05T10:06:32",
    "ram_used": 15209,
    "ram_total": 62841,
    "batch_size": 64,
    "bar_start_end": true
  },
  {
    "timestamp": "2025-11-05T10:06:33",
    "ram_used": 15209,
    "ram_total": 62841,
    "batch_size": 64,
    "bar_start_end": false
  },
  {
    "timestamp": "2025-11-05T10:06:34",
    "ram_used": 15209,
    "ram_total": 62841,
    "batch_size": 64,
    "bar_start_end": false
  },
  {
    "timestamp": "2025-11-05T10:06:35",
    "ram_used": 15209,
    "ram_total": 62841,
    "batch_size": 64,
    "bar_start_end": false
  },
  {
    "timestamp": "2025-11-05T10:06:36",
    "ram_used": 15209,
    "ram_total": 62841,
    "batch_size": 64,
    "bar_start_end": false
  },
  {
    "timestamp": "2025-11-05T10:06:37",
    "ram_used": 15209,
    "ram_total": 62841,
    "batch_size": 64,
    "bar_start_end": false
  },
  {
    "timestamp": "2025-11-05T10:06:38",
    "ram_used": 15209,
    "ram_total": 62841,
    "batch_size": 64,
    "bar_start_end": false
  },
  {
    "timestamp": "2025-11-05T10:06:39",
    "ram_used": 15209,
    "ram_total": 62841,
    "batch_size": 64,
    "bar_start_end": false
  },
  {
    "timestamp": "2025-11-05T10:06:40",
    "ram_used": 15210,
    "ram_total": 62841,
    "batch_size": 64,
    "bar_start_end": false
  },
  {
    "timestamp": "2025-11-05T10:06:41",
    "ram_used": 15210,
    "ram_total": 62841,
    "batch_size": 64,
    "bar_start_end": true
  },
  {
    "timestamp": "2025-11-05T10:06:42",
    "ram_used": 15210,
    "ram_total": 62841,
    "batch_size": 64,
    "bar_start_end": false
  },
  {
    "timestamp": "2025-11-05T10:06:43",
    "ram_used": 15210,
    "ram_total": 62841,
    "batch_size": 64,
    "bar_start_end": false
  },
  {
    "timestamp": "2025-11-05T10:06:44",
    "ram_used": 15210,
    "ram_total": 62841,
    "batch_size": 64,
    "bar_start_end": false
  },
  {
    "timestamp": "2025-11-05T10:06:46",
    "ram_used": 15210,
    "ram_total": 62841,
    "batch_size": 64,
    "bar_start_end": false
  },
  {
    "timestamp": "2025-11-05T10:06:47",
    "ram_used": 15210,
    "ram_total": 62841,
    "batch_size": 64,
    "bar_start_end": false
  },
  {
    "timestamp": "2025-11-05T10:06:48",
    "ram_used": 15210,
    "ram_total": 62841,
    "batch_size": 64,
    "bar_start_end": false
  },
  {
    "timestamp": "2025-11-05T10:06:49",
    "ram_used": 15210,
    "ram_total": 62841,
    "batch_size": 64,
    "bar_start_end": false
  },
  {
    "timestamp": "2025-11-05T10:06:50",
    "ram_used": 15208,
    "ram_total": 62841,
    "batch_size": 64,
    "bar_start_end": false
  },
  {
    "timestamp": "2025-11-05T10:06:51",
    "ram_used": 15208,
    "ram_total": 62841,
    "batch_size": 64,
    "bar_start_end": false
  },
  {
    "timestamp": "2025-11-05T10:07:01",
    "ram_used": 15217,
    "ram_total": 62841,
    "batch_size": 128,
    "bar_start_end": false
  },
  {
    "timestamp": "2025-11-05T10:07:02",
    "ram_used": 15217,
    "ram_total": 62841,
    "batch_size": 128,
    "bar_start_end": false
  },
  {
    "timestamp": "2025-11-05T10:07:03",
    "ram_used": 15216,
    "ram_total": 62841,
    "batch_size": 128,
    "bar_start_end": false
  },
  {
    "timestamp": "2025-11-05T10:07:04",
    "ram_used": 15216,
    "ram_total": 62841,
    "batch_size": 128,
    "bar_start_end": false
  },
  {
    "timestamp": "2025-11-05T10:07:05",
    "ram_used": 15216,
    "ram_total": 62841,
    "batch_size": 128,
    "bar_start_end": false
  },
  {
    "timestamp": "2025-11-05T10:07:06",
    "ram_used": 15216,
    "ram_total": 62841,
    "batch_size": 128,
    "bar_start_end": false
  },
  {
    "timestamp": "2025-11-05T10:07:07",
    "ram_used": 15216,
    "ram_total": 62841,
    "batch_size": 128,
    "bar_start_end": false
  },
  {
    "timestamp": "2025-11-05T10:07:08",
    "ram_used": 15216,
    "ram_total": 62841,
    "batch_size": 128,
    "bar_start_end": false
  },
  {
    "timestamp": "2025-11-05T10:07:09",
    "ram_used": 15216,
    "ram_total": 62841,
    "batch_size": 128,
    "bar_start_end": false
  },
  {
    "timestamp": "2025-11-05T10:07:10",
    "ram_used": 15217,
    "ram_total": 62841,
    "batch_size": 128,
    "bar_start_end": true
  },
  {
    "timestamp": "2025-11-05T10:07:11",
    "ram_used": 15217,
    "ram_total": 62841,
    "batch_size": 128,
    "bar_start_end": false
  },
  {
    "timestamp": "2025-11-05T10:07:12",
    "ram_used": 15217,
    "ram_total": 62841,
    "batch_size": 128,
    "bar_start_end": false
  },
  {
    "timestamp": "2025-11-05T10:07:13",
    "ram_used": 15217,
    "ram_total": 62841,
    "batch_size": 128,
    "bar_start_end": false
  },
  {
    "timestamp": "2025-11-05T10:07:14",
    "ram_used": 15217,
    "ram_total": 62841,
    "batch_size": 128,
    "bar_start_end": false
  },
  {
    "timestamp": "2025-11-05T10:07:15",
    "ram_used": 15218,
    "ram_total": 62841,
    "batch_size": 128,
    "bar_start_end": false
  },
  {
    "timestamp": "2025-11-05T10:07:17",
    "ram_used": 15218,
    "ram_total": 62841,
    "batch_size": 128,
    "bar_start_end": false
  },
  {
    "timestamp": "2025-11-05T10:07:18",
    "ram_used": 15218,
    "ram_total": 62841,
    "batch_size": 128,
    "bar_start_end": true
  },
  {
    "timestamp": "2025-11-05T10:07:19",
    "ram_used": 15219,
    "ram_total": 62841,
    "batch_size": 128,
    "bar_start_end": false
  },
  {
    "timestamp": "2025-11-05T10:07:20",
    "ram_used": 15219,
    "ram_total": 62841,
    "batch_size": 128,
    "bar_start_end": false
  },
  {
    "timestamp": "2025-11-05T10:07:21",
    "ram_used": 15219,
    "ram_total": 62841,
    "batch_size": 128,
    "bar_start_end": false
  },
  {
    "timestamp": "2025-11-05T10:07:22",
    "ram_used": 15219,
    "ram_total": 62841,
    "batch_size": 128,
    "bar_start_end": false
  },
  {
    "timestamp": "2025-11-05T10:07:23",
    "ram_used": 15219,
    "ram_total": 62841,
    "batch_size": 128,
    "bar_start_end": false
  },
  {
    "timestamp": "2025-11-05T10:07:24",
    "ram_used": 15219,
    "ram_total": 62841,
    "batch_size": 128,
    "bar_start_end": false
  },
  {
    "timestamp": "2025-11-05T10:07:25",
    "ram_used": 15219,
    "ram_total": 62841,
    "batch_size": 128,
    "bar_start_end": false
  },
  {
    "timestamp": "2025-11-05T10:07:26",
    "ram_used": 15219,
    "ram_total": 62841,
    "batch_size": 128,
    "bar_start_end": false
  },
  {
    "timestamp": "2025-11-05T10:07:27",
    "ram_used": 15219,
    "ram_total": 62841,
    "batch_size": 128,
    "bar_start_end": false
  },
  {
    "timestamp": "2025-11-05T10:07:28",
    "ram_used": 15219,
    "ram_total": 62841,
    "batch_size": 128,
    "bar_start_end": false
  },
  {
    "timestamp": "2025-11-05T10:07:38",
    "ram_used": 15265,
    "ram_total": 62841,
    "batch_size": 256,
    "bar_start_end": false
  },
  {
    "timestamp": "2025-11-05T10:07:39",
    "ram_used": 15266,
    "ram_total": 62841,
    "batch_size": 256,
    "bar_start_end": false
  },
  {
    "timestamp": "2025-11-05T10:07:40",
    "ram_used": 15266,
    "ram_total": 62841,
    "batch_size": 256,
    "bar_start_end": false
  },
  {
    "timestamp": "2025-11-05T10:07:41",
    "ram_used": 15264,
    "ram_total": 62841,
    "batch_size": 256,
    "bar_start_end": false
  },
  {
    "timestamp": "2025-11-05T10:07:42",
    "ram_used": 15264,
    "ram_total": 62841,
    "batch_size": 256,
    "bar_start_end": false
  },
  {
    "timestamp": "2025-11-05T10:07:43",
    "ram_used": 15264,
    "ram_total": 62841,
    "batch_size": 256,
    "bar_start_end": false
  },
  {
    "timestamp": "2025-11-05T10:07:44",
    "ram_used": 15264,
    "ram_total": 62841,
    "batch_size": 256,
    "bar_start_end": false
  },
  {
    "timestamp": "2025-11-05T10:07:45",
    "ram_used": 15264,
    "ram_total": 62841,
    "batch_size": 256,
    "bar_start_end": false
  },
  {
    "timestamp": "2025-11-05T10:07:46",
    "ram_used": 15264,
    "ram_total": 62841,
    "batch_size": 256,
    "bar_start_end": false
  },
  {
    "timestamp": "2025-11-05T10:07:47",
    "ram_used": 15268,
    "ram_total": 62841,
    "batch_size": 256,
    "bar_start_end": true
  },
  {
    "timestamp": "2025-11-05T10:07:48",
    "ram_used": 15269,
    "ram_total": 62841,
    "batch_size": 256,
    "bar_start_end": false
  },
  {
    "timestamp": "2025-11-05T10:07:49",
    "ram_used": 15269,
    "ram_total": 62841,
    "batch_size": 256,
    "bar_start_end": false
  },
  {
    "timestamp": "2025-11-05T10:07:50",
    "ram_used": 15269,
    "ram_total": 62841,
    "batch_size": 256,
    "bar_start_end": false
  },
  {
    "timestamp": "2025-11-05T10:07:51",
    "ram_used": 15269,
    "ram_total": 62841,
    "batch_size": 256,
    "bar_start_end": false
  },
  {
    "timestamp": "2025-11-05T10:07:52",
    "ram_used": 15269,
    "ram_total": 62841,
    "batch_size": 256,
    "bar_start_end": false
  },
  {
    "timestamp": "2025-11-05T10:07:53",
    "ram_used": 15269,
    "ram_total": 62841,
    "batch_size": 256,
    "bar_start_end": false
  },
  {
    "timestamp": "2025-11-05T10:07:54",
    "ram_used": 15269,
    "ram_total": 62841,
    "batch_size": 256,
    "bar_start_end": true
  },
  {
    "timestamp": "2025-11-05T10:07:55",
    "ram_used": 15269,
    "ram_total": 62841,
    "batch_size": 256,
    "bar_start_end": false
  },
  {
    "timestamp": "2025-11-05T10:07:56",
    "ram_used": 15269,
    "ram_total": 62841,
    "batch_size": 256,
    "bar_start_end": false
  },
  {
    "timestamp": "2025-11-05T10:07:58",
    "ram_used": 15269,
    "ram_total": 62841,
    "batch_size": 256,
    "bar_start_end": false
  },
  {
    "timestamp": "2025-11-05T10:07:59",
    "ram_used": 15269,
    "ram_total": 62841,
    "batch_size": 256,
    "bar_start_end": false
  },
  {
    "timestamp": "2025-11-05T10:08:00",
    "ram_used": 15269,
    "ram_total": 62841,
    "batch_size": 256,
    "bar_start_end": false
  },
  {
    "timestamp": "2025-11-05T10:08:01",
    "ram_used": 15269,
    "ram_total": 62841,
    "batch_size": 256,
    "bar_start_end": false
  },
  {
    "timestamp": "2025-11-05T10:08:02",
    "ram_used": 15269,
    "ram_total": 62841,
    "batch_size": 256,
    "bar_start_end": false
  },
  {
    "timestamp": "2025-11-05T10:08:03",
    "ram_used": 15270,
    "ram_total": 62841,
    "batch_size": 256,
    "bar_start_end": false
  },
  {
    "timestamp": "2025-11-05T10:08:04",
    "ram_used": 15269,
    "ram_total": 62841,
    "batch_size": 256,
    "bar_start_end": false
  },
  {
    "timestamp": "2025-11-05T10:08:05",
    "ram_used": 15269,
    "ram_total": 62841,
    "batch_size": 256,
    "bar_start_end": false
  },
  {
    "timestamp": "2025-11-05T10:08:14",
    "ram_used": 15297,
    "ram_total": 62841,
    "batch_size": 512,
    "bar_start_end": false
  },
  {
    "timestamp": "2025-11-05T10:08:15",
    "ram_used": 15297,
    "ram_total": 62841,
    "batch_size": 512,
    "bar_start_end": false
  },
  {
    "timestamp": "2025-11-05T10:08:16",
    "ram_used": 15297,
    "ram_total": 62841,
    "batch_size": 512,
    "bar_start_end": false
  },
  {
    "timestamp": "2025-11-05T10:08:18",
    "ram_used": 15297,
    "ram_total": 62841,
    "batch_size": 512,
    "bar_start_end": false
  },
  {
    "timestamp": "2025-11-05T10:08:19",
    "ram_used": 15297,
    "ram_total": 62841,
    "batch_size": 512,
    "bar_start_end": false
  },
  {
    "timestamp": "2025-11-05T10:08:20",
    "ram_used": 15297,
    "ram_total": 62841,
    "batch_size": 512,
    "bar_start_end": false
  },
  {
    "timestamp": "2025-11-05T10:08:21",
    "ram_used": 15297,
    "ram_total": 62841,
    "batch_size": 512,
    "bar_start_end": false
  },
  {
    "timestamp": "2025-11-05T10:08:22",
    "ram_used": 15297,
    "ram_total": 62841,
    "batch_size": 512,
    "bar_start_end": false
  },
  {
    "timestamp": "2025-11-05T10:08:23",
    "ram_used": 15297,
    "ram_total": 62841,
    "batch_size": 512,
    "bar_start_end": false
  },
  {
    "timestamp": "2025-11-05T10:08:24",
    "ram_used": 15306,
    "ram_total": 62841,
    "batch_size": 512,
    "bar_start_end": true
  },
  {
    "timestamp": "2025-11-05T10:08:25",
    "ram_used": 15308,
    "ram_total": 62841,
    "batch_size": 512,
    "bar_start_end": false
  },
  {
    "timestamp": "2025-11-05T10:08:26",
    "ram_used": 15321,
    "ram_total": 62841,
    "batch_size": 512,
    "bar_start_end": false
  },
  {
    "timestamp": "2025-11-05T10:08:27",
    "ram_used": 15304,
    "ram_total": 62841,
    "batch_size": 512,
    "bar_start_end": false
  },
  {
    "timestamp": "2025-11-05T10:08:28",
    "ram_used": 15316,
    "ram_total": 62841,
    "batch_size": 512,
    "bar_start_end": false
  },
  {
    "timestamp": "2025-11-05T10:08:29",
    "ram_used": 15320,
    "ram_total": 62841,
    "batch_size": 512,
    "bar_start_end": false
  },
  {
    "timestamp": "2025-11-05T10:08:30",
    "ram_used": 15320,
    "ram_total": 62841,
    "batch_size": 512,
    "bar_start_end": false
  },
  {
    "timestamp": "2025-11-05T10:08:31",
    "ram_used": 15320,
    "ram_total": 62841,
    "batch_size": 512,
    "bar_start_end": true
  },
  {
    "timestamp": "2025-11-05T10:08:32",
    "ram_used": 15320,
    "ram_total": 62841,
    "batch_size": 512,
    "bar_start_end": false
  },
  {
    "timestamp": "2025-11-05T10:08:33",
    "ram_used": 15320,
    "ram_total": 62841,
    "batch_size": 512,
    "bar_start_end": false
  },
  {
    "timestamp": "2025-11-05T10:08:34",
    "ram_used": 15320,
    "ram_total": 62841,
    "batch_size": 512,
    "bar_start_end": false
  },
  {
    "timestamp": "2025-11-05T10:08:35",
    "ram_used": 15320,
    "ram_total": 62841,
    "batch_size": 512,
    "bar_start_end": false
  },
  {
    "timestamp": "2025-11-05T10:08:36",
    "ram_used": 15320,
    "ram_total": 62841,
    "batch_size": 512,
    "bar_start_end": false
  },
  {
    "timestamp": "2025-11-05T10:08:37",
    "ram_used": 15320,
    "ram_total": 62841,
    "batch_size": 512,
    "bar_start_end": false
  },
  {
    "timestamp": "2025-11-05T10:08:38",
    "ram_used": 15320,
    "ram_total": 62841,
    "batch_size": 512,
    "bar_start_end": false
  },
  {
    "timestamp": "2025-11-05T10:08:39",
    "ram_used": 15320,
    "ram_total": 62841,
    "batch_size": 512,
    "bar_start_end": false
  },
  {
    "timestamp": "2025-11-05T10:08:40",
    "ram_used": 15318,
    "ram_total": 62841,
    "batch_size": 512,
    "bar_start_end": false
  },
  {
    "timestamp": "2025-11-05T10:08:51",
    "ram_used": 15317,
    "ram_total": 62841,
    "batch_size": 1024,
    "bar_start_end": false
  },
  {
    "timestamp": "2025-11-05T10:08:52",
    "ram_used": 15316,
    "ram_total": 62841,
    "batch_size": 1024,
    "bar_start_end": false
  },
  {
    "timestamp": "2025-11-05T10:08:53",
    "ram_used": 15317,
    "ram_total": 62841,
    "batch_size": 1024,
    "bar_start_end": false
  },
  {
    "timestamp": "2025-11-05T10:08:54",
    "ram_used": 15316,
    "ram_total": 62841,
    "batch_size": 1024,
    "bar_start_end": false
  },
  {
    "timestamp": "2025-11-05T10:08:55",
    "ram_used": 15317,
    "ram_total": 62841,
    "batch_size": 1024,
    "bar_start_end": false
  },
  {
    "timestamp": "2025-11-05T10:08:56",
    "ram_used": 15316,
    "ram_total": 62841,
    "batch_size": 1024,
    "bar_start_end": false
  },
  {
    "timestamp": "2025-11-05T10:08:57",
    "ram_used": 15316,
    "ram_total": 62841,
    "batch_size": 1024,
    "bar_start_end": false
  },
  {
    "timestamp": "2025-11-05T10:08:58",
    "ram_used": 15316,
    "ram_total": 62841,
    "batch_size": 1024,
    "bar_start_end": false
  },
  {
    "timestamp": "2025-11-05T10:08:59",
    "ram_used": 15316,
    "ram_total": 62841,
    "batch_size": 1024,
    "bar_start_end": false
  },
  {
    "timestamp": "2025-11-05T10:09:00",
    "ram_used": 15344,
    "ram_total": 62841,
    "batch_size": 1024,
    "bar_start_end": true
  },
  {
    "timestamp": "2025-11-05T10:09:01",
    "ram_used": 15355,
    "ram_total": 62841,
    "batch_size": 1024,
    "bar_start_end": false
  },
  {
    "timestamp": "2025-11-05T10:09:02",
    "ram_used": 15355,
    "ram_total": 62841,
    "batch_size": 1024,
    "bar_start_end": false
  },
  {
    "timestamp": "2025-11-05T10:09:03",
    "ram_used": 15356,
    "ram_total": 62841,
    "batch_size": 1024,
    "bar_start_end": false
  },
  {
    "timestamp": "2025-11-05T10:09:04",
    "ram_used": 15355,
    "ram_total": 62841,
    "batch_size": 1024,
    "bar_start_end": false
  },
  {
    "timestamp": "2025-11-05T10:09:05",
    "ram_used": 15354,
    "ram_total": 62841,
    "batch_size": 1024,
    "bar_start_end": false
  },
  {
    "timestamp": "2025-11-05T10:09:06",
    "ram_used": 15354,
    "ram_total": 62841,
    "batch_size": 1024,
    "bar_start_end": true
  },
  {
    "timestamp": "2025-11-05T10:09:07",
    "ram_used": 15354,
    "ram_total": 62841,
    "batch_size": 1024,
    "bar_start_end": false
  },
  {
    "timestamp": "2025-11-05T10:09:08",
    "ram_used": 15354,
    "ram_total": 62841,
    "batch_size": 1024,
    "bar_start_end": false
  },
  {
    "timestamp": "2025-11-05T10:09:09",
    "ram_used": 15354,
    "ram_total": 62841,
    "batch_size": 1024,
    "bar_start_end": false
  },
  {
    "timestamp": "2025-11-05T10:09:10",
    "ram_used": 15354,
    "ram_total": 62841,
    "batch_size": 1024,
    "bar_start_end": false
  },
  {
    "timestamp": "2025-11-05T10:09:11",
    "ram_used": 15354,
    "ram_total": 62841,
    "batch_size": 1024,
    "bar_start_end": false
  },
  {
    "timestamp": "2025-11-05T10:09:12",
    "ram_used": 15354,
    "ram_total": 62841,
    "batch_size": 1024,
    "bar_start_end": false
  },
  {
    "timestamp": "2025-11-05T10:09:13",
    "ram_used": 15354,
    "ram_total": 62841,
    "batch_size": 1024,
    "bar_start_end": false
  },
  {
    "timestamp": "2025-11-05T10:09:14",
    "ram_used": 15354,
    "ram_total": 62841,
    "batch_size": 1024,
    "bar_start_end": false
  },
  {
    "timestamp": "2025-11-05T10:09:15",
    "ram_used": 15354,
    "ram_total": 62841,
    "batch_size": 1024,
    "bar_start_end": false
  },
  {
    "timestamp": "2025-11-05T10:09:16",
    "ram_used": 15354,
    "ram_total": 62841,
    "batch_size": 1024,
    "bar_start_end": false
  }
]